{"order":["featured_collection","featured_product_fUHQJA"],"sections":{"featured_collection":{"settings":{"collection":"all","color_scheme":"scheme-1","columns_desktop":4,"columns_mobile":"2","description":"","description_style":"body","enable_desktop_slider":false,"full_width":false,"heading_size":"h2","image_ratio":"square","image_shape":"default","padding_bottom":36,"padding_top":0,"products_to_show":24,"quick_add":"none","show_description":false,"show_rating":false,"show_secondary_image":true,"show_vendor":false,"show_view_all":true,"swipe_on_mobile":false,"title":"","view_all_style":"outline"},"type":"featured-collection"},"featured_product_fUHQJA":{"block_order":["text_ddX8XX","title_6WjBNc","price_mEzXVw","variant_picker_i4zFik","quantity_selector_zEwa9w","buy_buttons_eDTYAQ","share_fgCPXK"],"blocks":{"buy_buttons_eDTYAQ":{"settings":{"show_dynamic_checkout":true,"show_gift_card_recipient":true},"type":"buy_buttons"},"price_mEzXVw":{"settings":{},"type":"price"},"quantity_selector_zEwa9w":{"settings":{},"type":"quantity_selector"},"share_fgCPXK":{"settings":{"share_label":"Share"},"type":"share"},"text_ddX8XX":{"settings":{"text":"{{ section.settings.product.vendor }}","text_style":"uppercase"},"type":"text"},"title_6WjBNc":{"settings":{"heading_size":"h1"},"type":"title"},"variant_picker_i4zFik":{"settings":{"picker_type":"button","swatch_shape":"circle"},"type":"variant_picker"}},"settings":{"color_scheme":"scheme-d0e50468-479c-48b5-abd4-e091b2b42030","constrain_to_viewport":true,"enable_video_looping":false,"hide_variants":false,"image_zoom":"lightbox","media_fit":"contain","media_position":"left","media_size":"medium","padding_bottom":36,"padding_top":36,"product":"mahomes-kelse-2024","secondary_background":false},"type":"featured-product"}}}